camera/__init__.py
camera/camera.py
meerk40t_camera-0.1.9.dist-info/LICENSE
meerk40t_camera-0.1.9.dist-info/METADATA
meerk40t_camera-0.1.9.dist-info/WHEEL
meerk40t_camera-0.1.9.dist-info/entry_points.txt
meerk40t_camera-0.1.9.dist-info/top_level.txt
meerk40t_camera-0.1.9.dist-info/zip-safe
meerk40t_camera-0.1.9.dist-info/RECORD
